cli/__init__.py
cli/account.py
cli/auxiliary.py
cli/feedback.py
cli/login.py
cli/main.py
cli/service_principal.py
cli/util.py
komodo/APIResponseError.py
komodo/__init__.py
komodo/_vendored/__init__.py
komodo/_vendored/komodo_connector/__init__.py
komodo/_vendored/komodo_connector/connection.py
komodo/_vendored/komodo_connector/connection_creators/__init__.py
komodo/_vendored/komodo_connector/connection_creators/snowflake/__init__.py
komodo/_vendored/komodo_connector/connection_creators/snowflake/connect.py
komodo/_vendored/komodo_connector/connection_creators/snowflake/creator.py
komodo/_vendored/komodo_connector/connection_creators/snowflake/cursor.py
komodo/_vendored/komodo_connector/connection_creators/snowflake/komodo_auth.py
komodo/_vendored/komodo_connector/connection_creators/snowflake/network.py
komodo/_vendored/komodo_connector/connection_creators/snowflake/utils.py
komodo/_vendored/komodo_connector/connection_creators/snowflake_native/__init__.py
komodo/_vendored/komodo_connector/connection_creators/snowflake_native/creator.py
komodo/_vendored/komodo_connector/connection_creators/snowflake_rotate_keys/__init__.py
komodo/_vendored/komodo_connector/connection_creators/snowflake_rotate_keys/creator.py
komodo/_vendored/komodo_connector/connector.py
komodo/_vendored/komodo_connector/constants.py
komodo/_vendored/komodo_connector/creator.py
komodo/_vendored/komodo_connector/models.py
komodo/_vendored/komodo_connector/session.py
komodo/_vendored/komodo_connector/setup_driver.py
komodo/_vendored/komodo_sqlalchemy/__init__.py
komodo/_vendored/komodo_sqlalchemy/dialect.py
komodo/_vendored/komodo_sqlalchemy/komodo_engine_plugin.py
komodo/_vendored/snowflake_query_tag/__init__.py
komodo/_vendored/snowflake_query_tag/models.py
komodo/api/__init__.py
komodo/api/iam_api.py
komodo/api_client.py
komodo/api_response.py
komodo/auth/OAuthFlows.py
komodo/auth/Session.py
komodo/auth/constants.py
komodo/client.py
komodo/config.py
komodo/configuration.py
komodo/core/__init__.py
komodo-3.0.5.dist-info/WHEEL
komodo-3.0.5.dist-info/entry_points.txt
komodo-3.0.5.dist-info/METADATA
komodo-3.0.5.dist-info/RECORD
